{
  "formations": [
    {"id": 1, "name": "Superior", "description": "Nível de educação superior"},
    {"id": 2, "name": "Inferior", "description": "Nível de educação básico/médio"}
  ],
  "types": [
    {"id": 1, "name": "Bacharelado", "description": "Bacharelado"},
    {"id": 2, "name": "Tecnico", "description": "Técnico"},
    {"id": 3, "name": "Tecnologo", "description": "Tecnólogo"}
  ],
  "courses": [
    {"name": "Engenharia Civil", "formation_id": 1, "type_id": 1},
    {"name": "Engenharia de Software", "formation_id": 1, "type_id": 1},
    {"name": "Engenharia Elétrica", "formation_id": 1, "type_id": 1},
    {"name": "Engenharia Mecânica", "formation_id": 1, "type_id": 1},
    {"name": "Engenharia de Produção", "formation_id": 1, "type_id": 1},
    {"name": "Engenharia Química", "formation_id": 1, "type_id": 1},
    {"name": "Engenharia Ambiental", "formation_id": 1, "type_id": 1},
    {"name": "Engenharia Aeronáutica", "formation_id": 1, "type_id": 1},
    {"name": "Engenharia de Telecomunicações", "formation_id": 1, "type_id": 1},
    {"name": "Engenharia Biomédica", "formation_id": 1, "type_id": 1},
    {"name": "Medicina", "formation_id": 1, "type_id": 1},
    {"name": "Enfermagem", "formation_id": 1, "type_id": 1},
    {"name": "Odontologia", "formation_id": 1, "type_id": 1},
    {"name": "Farmácia", "formation_id": 1, "type_id": 1},
    {"name": "Psicologia", "formation_id": 1, "type_id": 1},
    {"name": "Fisioterapia", "formation_id": 1, "type_id": 1},
    {"name": "Nutrição", "formation_id": 1, "type_id": 1},
    {"name": "Fonoaudiologia", "formation_id": 1, "type_id": 1},
    {"name": "Veterinária", "formation_id": 1, "type_id": 1},
    {"name": "Terapia Ocupacional", "formation_id": 1, "type_id": 1},
    {"name": "Direito", "formation_id": 1, "type_id": 1},
    {"name": "Administração", "formation_id": 1, "type_id": 1},
    {"name": "Contabilidade", "formation_id": 1, "type_id": 1},
    {"name": "Economia", "formation_id": 1, "type_id": 1},
    {"name": "Educação", "formation_id": 1, "type_id": 1},
    {"name": "História", "formation_id": 1, "type_id": 1},
    {"name": "Geografia", "formation_id": 1, "type_id": 1},
    {"name": "Sociologia", "formation_id": 1, "type_id": 1},
    {"name": "Filosofia", "formation_id": 1, "type_id": 1},
    {"name": "Letras", "formation_id": 1, "type_id": 1},
    {"name": "Matemática", "formation_id": 1, "type_id": 1},
    {"name": "Física", "formation_id": 1, "type_id": 1},
    {"name": "Química", "formation_id": 1, "type_id": 1},
    {"name": "Biologia", "formation_id": 1, "type_id": 1},
    {"name": "Estatística", "formation_id": 1, "type_id": 1},
    {"name": "Ciência da Computação", "formation_id": 1, "type_id": 1},
    {"name": "Astronomia", "formation_id": 1, "type_id": 1},
    {"name": "Geologia", "formation_id": 1, "type_id": 1},
    {"name": "Arquitetura", "formation_id": 1, "type_id": 1},
    {"name": "Design Gráfico", "formation_id": 1, "type_id": 1},
    {"name": "Artes Visuais", "formation_id": 1, "type_id": 1},
    {"name": "Música", "formation_id": 1, "type_id": 1},
    {"name": "Cinema", "formation_id": 1, "type_id": 1},
    {"name": "Dança", "formation_id": 1, "type_id": 1},
    {"name": "Teatro", "formation_id": 1, "type_id": 1},
    {"name": "Moda", "formation_id": 1, "type_id": 1},
    {"name": "Agronomia", "formation_id": 1, "type_id": 1},
    {"name": "Zootecnia", "formation_id": 1, "type_id": 1},
    {"name": "Engenharia Agrícola", "formation_id": 1, "type_id": 1},
    {"name": "Silvicultura", "formation_id": 1, "type_id": 1},
    {"name": "Aquicultura", "formation_id": 1, "type_id": 1},
    {"name": "Engenharia de Controle e Automação", "formation_id": 1, "type_id": 1},
    {"name": "Engenharia de Materiais", "formation_id": 1, "type_id": 1},
    {"name": "Engenharia Nuclear", "formation_id": 1, "type_id": 1},
    {"name": "Engenharia Cartográfica", "formation_id": 1, "type_id": 1},
    {"name": "Engenharia de Alimentos", "formation_id": 1, "type_id": 1},
    {"name": "Engenharia de Minas", "formation_id": 1, "type_id": 1},
    {"name": "Engenharia Florestal", "formation_id": 1, "type_id": 1},
    {"name": "Engenharia Hídrica", "formation_id": 1, "type_id": 1},
    {"name": "Engenharia Sanitária", "formation_id": 1, "type_id": 1},
    {"name": "Engenharia Petroquímica", "formation_id": 1, "type_id": 1},
    {"name": "Medicina Veterinária", "formation_id": 1, "type_id": 1},
    {"name": "Podologia", "formation_id": 1, "type_id": 1},
    {"name": "Educação Física", "formation_id": 1, "type_id": 1},
    {"name": "Biomedicina", "formation_id": 1, "type_id": 1},
    {"name": "Ciências Biológicas", "formation_id": 1, "type_id": 1},
    {"name": "Jornalismo", "formation_id": 1, "type_id": 1},
    {"name": "Publicidade e Propaganda", "formation_id": 1, "type_id": 1},
    {"name": "Relações Públicas", "formation_id": 1, "type_id": 1},
    {"name": "Ciências Políticas", "formation_id": 1, "type_id": 1},
    {"name": "Teologia", "formation_id": 1, "type_id": 1},
    {"name": "Secretariado Executivo", "formation_id": 1, "type_id": 1},
    {"name": "Serviço Social", "formation_id": 1, "type_id": 1},
    {"name": "Biblioteconomia", "formation_id": 1, "type_id": 1},
    {"name": "Arquivologia", "formation_id": 1, "type_id": 1},
    {"name": "Museologia", "formation_id": 1, "type_id": 1},
    {"name": "Meteorologia", "formation_id": 1, "type_id": 1},
    {"name": "Oceanografia", "formation_id": 1, "type_id": 1},
    {"name": "Arquitetura e Urbanismo", "formation_id": 1, "type_id": 1},
    {"name": "Design de Moda", "formation_id": 1, "type_id": 1},
    {"name": "Design de Interiores", "formation_id": 1, "type_id": 1},
    {"name": "Design Industrial", "formation_id": 1, "type_id": 1},
    {"name": "Cinema e Audiovisual", "formation_id": 1, "type_id": 1},
    {"name": "Recursos Humanos", "formation_id": 1, "type_id": 1},
    {"name": "Marketing", "formation_id": 1, "type_id": 1},
    {"name": "Gestão da Qualidade", "formation_id": 1, "type_id": 1},
    {"name": "Hotelaria e Turismo", "formation_id": 1, "type_id": 1},
    {"name": "Relações Internacionais", "formation_id": 1, "type_id": 1},
    {"name": "Estudos Estratégicos", "formation_id": 1, "type_id": 1},
    {"name": "Análise de Sistemas", "formation_id": 1, "type_id": 1},
    {"name": "Técnico em Eletrônica", "formation_id": 2, "type_id": 2},
    {"name": "Técnico em Programação", "formation_id": 2, "type_id": 2},
    {"name": "Técnico em Redes", "formation_id": 2, "type_id": 2},
    {"name": "Técnico em Administração", "formation_id": 2, "type_id": 2},
    {"name": "Técnico em Eletrotécnica", "formation_id": 2, "type_id": 2},
    {"name": "Técnico em Segurança do Trabalho", "formation_id": 2, "type_id": 2},
    {"name": "Técnico em Logística", "formation_id": 2, "type_id": 2},
    {"name": "Técnico em Gastronomia", "formation_id": 2, "type_id": 2},
    {"name": "Técnico em Farmácia", "formation_id": 2, "type_id": 2},
    {"name": "Técnico em Radiologia", "formation_id": 2, "type_id": 2},
    {"name": "Técnico em Enfermagem", "formation_id": 2, "type_id": 2},
    {"name": "Técnico em Veterinária", "formation_id": 2, "type_id": 2},
    {"name": "Técnico em Análises Clínicas", "formation_id": 2, "type_id": 2},
    {"name": "Técnico em Agrimensura", "formation_id": 2, "type_id": 2},
    {"name": "Técnico em Mecânica", "formation_id": 2, "type_id": 2},
    {"name": "Técnico em Edificações", "formation_id": 2, "type_id": 2},
    {"name": "Técnico em Metalurgia", "formation_id": 2, "type_id": 2},
    {"name": "Técnico em Têxtil", "formation_id": 2, "type_id": 2},
    {"name": "Técnico em Óptica", "formation_id": 2, "type_id": 2},
    {"name": "Técnico em Laboratório", "formation_id": 2, "type_id": 2},
    {"name": "Técnico em Informática", "formation_id": 2, "type_id": 2},
    {"name": "Técnico em Computação Gráfica", "formation_id": 2, "type_id": 2},
    {"name": "Técnico em Telecomunicações", "formation_id": 2, "type_id": 2},
    {"name": "Técnico em Refrigeração", "formation_id": 2, "type_id": 2},
    {"name": "Técnico em Ar Condicionado", "formation_id": 2, "type_id": 2},
    {"name": "Técnico em Automoção", "formation_id": 2, "type_id": 2},
    {"name": "Técnico em Solda", "formation_id": 2, "type_id": 2},
    {"name": "Técnico em Usinagem", "formation_id": 2, "type_id": 2},
    {"name": "Técnico em Torneiro Mecânico", "formation_id": 2, "type_id": 2},
    {"name": "Técnico em Marcenaria", "formation_id": 2, "type_id": 2},
    {"name": "Técnico em Móveis", "formation_id": 2, "type_id": 2},
    {"name": "Técnico em Confecção", "formation_id": 2, "type_id": 2},
    {"name": "Técnico em Calçados", "formation_id": 2, "type_id": 2},
    {"name": "Técnico em Artes do Couro", "formation_id": 2, "type_id": 2},
    {"name": "Técnico em Panificação", "formation_id": 2, "type_id": 2},
    {"name": "Técnico em Culinária", "formation_id": 2, "type_id": 2},
    {"name": "Técnico em Hotelaria", "formation_id": 2, "type_id": 2},
    {"name": "Técnico em Turismo", "formation_id": 2, "type_id": 2},
    {"name": "Técnico em Educação Física", "formation_id": 2, "type_id": 2},
    {"name": "Técnico em Desportos", "formation_id": 2, "type_id": 2},
    {"name": "Técnico em Paisagismo", "formation_id": 2, "type_id": 2},
    {"name": "Técnico em Floricultura", "formation_id": 2, "type_id": 2},
    {"name": "Técnico em Fruticultura", "formation_id": 2, "type_id": 2},
    {"name": "Técnico em Agricultura", "formation_id": 2, "type_id": 2},
    {"name": "Técnico em Pecuária", "formation_id": 2, "type_id": 2},
    {"name": "Técnico em Apicultura", "formation_id": 2, "type_id": 2},
    {"name": "Técnico em Piscicultura", "formation_id": 2, "type_id": 2},
    {"name": "Técnico em Aquacultura", "formation_id": 2, "type_id": 2},
    {"name": "Técnico em Manutenção de Máquinas", "formation_id": 2, "type_id": 2},
    {"name": "Técnico em Manutenção Industrial", "formation_id": 2, "type_id": 2},
    {"name": "Técnico em Manutenção de Equipamentos Médicos", "formation_id": 2, "type_id": 2},
    {"name": "Técnico em Instrumentação", "formation_id": 2, "type_id": 2},
    {"name": "Técnico em Geologia", "formation_id": 2, "type_id": 2},
    {"name": "Técnico em Mineração", "formation_id": 2, "type_id": 2},
    {"name": "Técnico em Petróleo", "formation_id": 2, "type_id": 2},
    {"name": "Técnico em Gás Natural", "formation_id": 2, "type_id": 2},
    {"name": "Técnico em Energia Solar", "formation_id": 2, "type_id": 2},
    {"name": "Técnico em Energia Eólica", "formation_id": 2, "type_id": 2},
    {"name": "Técnico em Hidrelétrica", "formation_id": 2, "type_id": 2},
    {"name": "Técnico em Tratamento de Água", "formation_id": 2, "type_id": 2},
    {"name": "Técnico em Resíduos Sólidos", "formation_id": 2, "type_id": 2},
    {"name": "Técnico em Controle Ambiental", "formation_id": 2, "type_id": 2},
    {"name": "Análise e Desenvolvimento de Sistemas", "formation_id": 1, "type_id": 3},
    {"name": "Gestão em Tecnologia da Informação", "formation_id": 1, "type_id": 3},
    {"name": "Redes de Computadores", "formation_id": 1, "type_id": 3},
    {"name": "Banco de Dados", "formation_id": 1, "type_id": 3},
    {"name": "Segurança da Informação", "formation_id": 1, "type_id": 3},
    {"name": "Big Data", "formation_id": 1, "type_id": 3},
    {"name": "Cloud Computing", "formation_id": 1, "type_id": 3},
    {"name": "Inteligência Artificial", "formation_id": 1, "type_id": 3},
    {"name": "Gestão Comercial", "formation_id": 1, "type_id": 3},
    {"name": "Logística", "formation_id": 1, "type_id": 3},
    {"name": "Gestão de Recursos Humanos", "formation_id": 1, "type_id": 3},
    {"name": "Gestão Financeira", "formation_id": 1, "type_id": 3},
    {"name": "Gestão de Projetos", "formation_id": 1, "type_id": 3},
    {"name": "Gestão Pública", "formation_id": 1, "type_id": 3},
    {"name": "Turismo", "formation_id": 1, "type_id": 3},
    {"name": "Hotelaria", "formation_id": 1, "type_id": 3},
    {"name": "Gastronomia", "formation_id": 1, "type_id": 3},
    {"name": "Eventos", "formation_id": 1, "type_id": 3},
    {"name": "Análises Clínicas", "formation_id": 1, "type_id": 3},
    {"name": "Radiologia", "formation_id": 1, "type_id": 3},
    {"name": "Prótese Dentária", "formation_id": 1, "type_id": 3},
    {"name": "Massoterapia", "formation_id": 1, "type_id": 3},
    {"name": "Segurança do Paciente", "formation_id": 1, "type_id": 3},
    {"name": "Design de Interiores", "formation_id": 1, "type_id": 3},
    {"name": "Design de Moda", "formation_id": 1, "type_id": 3},
    {"name": "Produção Audiovisual", "formation_id": 1, "type_id": 3},
    {"name": "Comunicação Social", "formation_id": 1, "type_id": 3},
    {"name": "Agroecologia", "formation_id": 1, "type_id": 3},
    {"name": "Gestão Ambiental", "formation_id": 1, "type_id": 3},
    {"name": "Energias Renováveis", "formation_id": 1, "type_id": 3},
    {"name": "Tecnólogo em Sustentabilidade", "formation_id": 1, "type_id": 3},
    {"name": "Tecnólogo em Comércio Exterior", "formation_id": 1, "type_id": 3},
    {"name": "Tecnólogo em Marketing Digital", "formation_id": 1, "type_id": 3},
    {"name": "Tecnólogo em E-commerce", "formation_id": 1, "type_id": 3},
    {"name": "Tecnólogo em Análise de Dados", "formation_id": 1, "type_id": 3},
    {"name": "Tecnólogo em Blockchain", "formation_id": 1, "type_id": 3},
    {"name": "Tecnólogo em Internet das Coisas", "formation_id": 1, "type_id": 3},
    {"name": "Tecnólogo em Realidade Virtual", "formation_id": 1, "type_id": 3},
    {"name": "Tecnólogo em Realidade Aumentada", "formation_id": 1, "type_id": 3},
    {"name": "Tecnólogo em Cibersegurança", "formation_id": 1, "type_id": 3},
    {"name": "Tecnólogo em Infraestrutura em TI", "formation_id": 1, "type_id": 3},
    {"name": "Tecnólogo em Suporte Técnico", "formation_id": 1, "type_id": 3},
    {"name": "Tecnólogo em Administração de Redes", "formation_id": 1, "type_id": 3},
    {"name": "Tecnólogo em Administração de Banco de Dados", "formation_id": 1, "type_id": 3},
    {"name": "Tecnólogo em Testing de Software", "formation_id": 1, "type_id": 3},
    {"name": "Tecnólogo em Testes Automatizados", "formation_id": 1, "type_id": 3},
    {"name": "Tecnólogo em Engenharia de Dados", "formation_id": 1, "type_id": 3},
    {"name": "Tecnólogo em Data Warehouse", "formation_id": 1, "type_id": 3},
    {"name": "Tecnólogo em ETL", "formation_id": 1, "type_id": 3},
    {"name": "Tecnólogo em Ciência de Dados", "formation_id": 1, "type_id": 3},
    {"name": "Tecnólogo em Programação de Jogos", "formation_id": 1, "type_id": 3},
    {"name": "Tecnólogo em Desenvolvimento de Jogos", "formation_id": 1, "type_id": 3},
    {"name": "Tecnólogo em Animação 3D", "formation_id": 1, "type_id": 3},
    {"name": "Tecnólogo em Modelagem 3D", "formation_id": 1, "type_id": 3},
    {"name": "Tecnólogo em Fotografia Digital", "formation_id": 1, "type_id": 3},
    {"name": "Tecnólogo em Edição de Vídeo", "formation_id": 1, "type_id": 3},
    {"name": "Tecnólogo em Pós-produção de Vídeo", "formation_id": 1, "type_id": 3},
    {"name": "Tecnólogo em Som Digital", "formation_id": 1, "type_id": 3},
    {"name": "Tecnólogo em Produção Musical", "formation_id": 1, "type_id": 3},
    {"name": "Tecnólogo em Design de Embalagem", "formation_id": 1, "type_id": 3},
    {"name": "Tecnólogo em Publicidade", "formation_id": 1, "type_id": 3},
    {"name": "Tecnólogo em Comunicação Visual", "formation_id": 1, "type_id": 3},
    {"name": "Tecnólogo em Gestão de Marketing", "formation_id": 1, "type_id": 3},
    {"name": "Tecnólogo em Recursos Humanos", "formation_id": 1, "type_id": 3},
    {"name": "Tecnólogo em Segurança do Trabalho", "formation_id": 1, "type_id": 3},
    {"name": "Tecnólogo em Higiene e Segurança", "formation_id": 1, "type_id": 3},
    {"name": "Tecnólogo em Saúde e Segurança", "formation_id": 1, "type_id": 3},
    {"name": "Tecnólogo em Qualidade", "formation_id": 1, "type_id": 3},
    {"name": "Tecnólogo em Gestão da Qualidade", "formation_id": 1, "type_id": 3},
    {"name": "Tecnólogo em Manutenção", "formation_id": 1, "type_id": 3},
    {"name": "Tecnólogo em Manutenção Industrial", "formation_id": 1, "type_id": 3},
    {"name": "Tecnólogo em Produção Industrial", "formation_id": 1, "type_id": 3},
    {"name": "Tecnólogo em Processos de Fabricação", "formation_id": 1, "type_id": 3},
    {"name": "Tecnólogo em Soldagem", "formation_id": 1, "type_id": 3},
    {"name": "Tecnólogo em Mecânica Automotiva", "formation_id": 1, "type_id": 3},
    {"name": "Tecnólogo em Tecnologia Automotiva", "formation_id": 1, "type_id": 3},
    {"name": "Tecnólogo em Aeronáutica", "formation_id": 1, "type_id": 3},
    {"name": "Tecnólogo em Aviação Civil", "formation_id": 1, "type_id": 3},
    {"name": "Tecnólogo em Navegação Aérea", "formation_id": 1, "type_id": 3},
    {"name": "Tecnólogo em Transporte Aéreo", "formation_id": 1, "type_id": 3},
    {"name": "Tecnólogo em Logística Aérea", "formation_id": 1, "type_id": 3},
    {"name": "Tecnólogo em Navegação Marítima", "formation_id": 1, "type_id": 3},
    {"name": "Tecnólogo em Portuária", "formation_id": 1, "type_id": 3},
    {"name": "Tecnólogo em Navegação Fluvial", "formation_id": 1, "type_id": 3},
    {"name": "Tecnólogo em Transporte Ferroviário", "formation_id": 1, "type_id": 3},
    {"name": "Tecnólogo em Transporte Rodoviário", "formation_id": 1, "type_id": 3},
    {"name": "Tecnólogo em Operações Portuárias", "formation_id": 1, "type_id": 3},
    {"name": "Tecnólogo em Manutenção Naval", "formation_id": 1, "type_id": 3},
    {"name": "Tecnólogo em Construção Naval", "formation_id": 1, "type_id": 3},
    {"name": "Tecnólogo em Telecomunicações", "formation_id": 1, "type_id": 3},
    {"name": "Tecnólogo em Redes de Telecomunicações", "formation_id": 1, "type_id": 3},
    {"name": "Tecnólogo em Radiocomunicações", "formation_id": 1, "type_id": 3},
    {"name": "Tecnólogo em Telefonia", "formation_id": 1, "type_id": 3},
    {"name": "Tecnólogo em Eletrônica Industrial", "formation_id": 1, "type_id": 3},
    {"name": "Tecnólogo em Eletrônica Embarcada", "formation_id": 1, "type_id": 3},
    {"name": "Tecnólogo em Eletrotécnica", "formation_id": 1, "type_id": 3},
    {"name": "Tecnólogo em Energias", "formation_id": 1, "type_id": 3},
    {"name": "Tecnólogo em Engenharia de Energia", "formation_id": 1, "type_id": 3},
    {"name": "Tecnólogo em Engenharia Elétrica", "formation_id": 1, "type_id": 3},
    {"name": "Tecnólogo em Engenharia Eletrônica", "formation_id": 1, "type_id": 3},
    {"name": "Tecnólogo em Engenharia Mecânica", "formation_id": 1, "type_id": 3},
    {"name": "Tecnólogo em Engenharia de Telecomunicações", "formation_id": 1, "type_id": 3},
    {"name": "Tecnólogo em Engenharia de Controle", "formation_id": 1, "type_id": 3},
    {"name": "Tecnólogo em Engenharia Ambiental", "formation_id": 1, "type_id": 3},
    {"name": "Tecnólogo em Engenharia Química", "formation_id": 1, "type_id": 3},
    {"name": "Tecnólogo em Engenharia de Alimentos", "formation_id": 1, "type_id": 3},
    {"name": "Tecnólogo em Engenharia de Biomassa", "formation_id": 1, "type_id": 3},
    {"name": "Tecnólogo em Engenharia Florestal", "formation_id": 1, "type_id": 3},
    {"name": "Tecnólogo em Engenharia Agronômica", "formation_id": 1, "type_id": 3},
    {"name": "Tecnólogo em Engenharia Zootécnica", "formation_id": 1, "type_id": 3},
    {"name": "Tecnólogo em Medicina Veterinária", "formation_id": 1, "type_id": 3},
    {"name": "Tecnólogo em Enfermagem", "formation_id": 1, "type_id": 3},
    {"name": "Tecnólogo em Farmácia", "formation_id": 1, "type_id": 3},
    {"name": "Tecnólogo em Fisioterapia", "formation_id": 1, "type_id": 3},
    {"name": "Tecnólogo em Nutrição", "formation_id": 1, "type_id": 3},
    {"name": "Tecnólogo em Psicologia", "formation_id": 1, "type_id": 3},
    {"name": "Tecnólogo em Estética e Cosmética", "formation_id": 1, "type_id": 3},
    {"name": "Tecnólogo em Cuidados Pessoais", "formation_id": 1, "type_id": 3},
    {"name": "Tecnólogo em Serviços de Saúde", "formation_id": 1, "type_id": 3},
    {"name": "Tecnólogo em Saúde Coletiva", "formation_id": 1, "type_id": 3},
    {"name": "Tecnólogo em Gestão em Saúde", "formation_id": 1, "type_id": 3},
    {"name": "Tecnólogo em Administração Hospitalar", "formation_id": 1, "type_id": 3},
    {"name": "Tecnólogo em Direito", "formation_id": 1, "type_id": 3},
    {"name": "Tecnólogo em Contabilidade", "formation_id": 1, "type_id": 3},
    {"name": "Tecnólogo em Administração de Empresas", "formation_id": 1, "type_id": 3},
    {"name": "Biomedicina", "formation_id": 1, "type_id": 1},
    {"name": "Ciências Contábeis", "formation_id": 1, "type_id": 1},
    {"name": "Gestão de Recursos Humanos", "formation_id": 1, "type_id": 1},
    {"name": "Comércio Exterior", "formation_id": 1, "type_id": 1},
    {"name": "Finanças", "formation_id": 1, "type_id": 1},
    {"name": "Administração Pública", "formation_id": 1, "type_id": 1},
    {"name": "Gestão em TI", "formation_id": 1, "type_id": 1},
    {"name": "Análise de Sistemas", "formation_id": 1, "type_id": 1},
    {"name": "Redes de Computadores", "formation_id": 1, "type_id": 1},
    {"name": "Ciência de Dados", "formation_id": 1, "type_id": 1},
    {"name": "Sistemas de Informação", "formation_id": 1, "type_id": 1},
    {"name": "Engenharia Biomédica", "formation_id": 1, "type_id": 1},
    {"name": "Engenharia de Controle e Automação", "formation_id": 1, "type_id": 1},
    {"name": "Engenharia de Materiais", "formation_id": 1, "type_id": 1},
    {"name": "Engenharia Nuclear", "formation_id": 1, "type_id": 1},
    {"name": "Engenharia Cartográfica", "formation_id": 1, "type_id": 1},
    {"name": "Engenharia de Alimentos", "formation_id": 1, "type_id": 1},
    {"name": "Engenharia de Minas", "formation_id": 1, "type_id": 1},
    {"name": "Engenharia Florestal", "formation_id": 1, "type_id": 1},
    {"name": "Engenharia Hídrica", "formation_id": 1, "type_id": 1},
    {"name": "Engenharia Sanitária", "formation_id": 1, "type_id": 1},
    {"name": "Engenharia Petroquímica", "formation_id": 1, "type_id": 1},
    {"name": "Engenharia Bioquímica", "formation_id": 1, "type_id": 1},
    {"name": "Engenharia de Sistemas", "formation_id": 1, "type_id": 1},
    {"name": "Engenharia da Computação", "formation_id": 1, "type_id": 1},
    {"name": "Engenharia Naval", "formation_id": 1, "type_id": 1},
    {"name": "Engenharia Automóvel", "formation_id": 1, "type_id": 1},
    {"name": "Engenharia de Transportes", "formation_id": 1, "type_id": 1},
    {"name": "Engenharia de Portos", "formation_id": 1, "type_id": 1},
    {"name": "Tecnólogo em Eletroeletrônica", "formation_id": 1, "type_id": 3},
    {"name": "Tecnólogo em Refrigeração e Climatização", "formation_id": 1, "type_id": 3},
    {"name": "Tecnólogo em Saneamento Ambiental", "formation_id": 1, "type_id": 3},
    {"name": "Tecnólogo em Meio Ambiente", "formation_id": 1, "type_id": 3},
    {"name": "Tecnólogo em Recursos Hídricos", "formation_id": 1, "type_id": 3},
    {"name": "Tecnólogo em Energias Alternativas", "formation_id": 1, "type_id": 3},
    {"name": "Tecnólogo em Gestão Ambiental e Sustentabilidade", "formation_id": 1, "type_id": 3},
    {"name": "Tecnólogo em Agricultura de Precisão", "formation_id": 1, "type_id": 3},
    {"name": "Tecnólogo em Fruticultura", "formation_id": 1, "type_id": 3},
    {"name": "Tecnólogo em Floricultura", "formation_id": 1, "type_id": 3},
    {"name": "Tecnólogo em Viticultura", "formation_id": 1, "type_id": 3},
    {"name": "Tecnólogo em Cafeicultura", "formation_id": 1, "type_id": 3},
    {"name": "Tecnólogo em Silvicultura", "formation_id": 1, "type_id": 3},
    {"name": "Tecnólogo em Apicultura", "formation_id": 1, "type_id": 3},
    {"name": "Tecnólogo em Meliponicultura", "formation_id": 1, "type_id": 3},
    {"name": "Tecnólogo em Ovinocultura", "formation_id": 1, "type_id": 3},
    {"name": "Tecnólogo em Caprinocultura", "formation_id": 1, "type_id": 3},
    {"name": "Tecnólogo em Bovinocultura", "formation_id": 1, "type_id": 3},
    {"name": "Tecnólogo em Equideocultura", "formation_id": 1, "type_id": 3},
    {"name": "Tecnólogo em Suinocultura", "formation_id": 1, "type_id": 3},
    {"name": "Tecnólogo em Avicultura", "formation_id": 1, "type_id": 3},
    {"name": "Tecnólogo em Piscicultura Comercial", "formation_id": 1, "type_id": 3},
    {"name": "Tecnólogo em Carcinicultura", "formation_id": 1, "type_id": 3},
    {"name": "Tecnólogo em Maricultura", "formation_id": 1, "type_id": 3},
    {"name": "Tecnólogo em Moluscultura", "formation_id": 1, "type_id": 3},
    {"name": "Tecnólogo em Ranicultura", "formation_id": 1, "type_id": 3},
    {"name": "Tecnólogo em Formação em Cavalos", "formation_id": 1, "type_id": 3},
    {"name": "Tecnólogo em Gestão Agropecuária", "formation_id": 1, "type_id": 3},
    {"name": "Tecnólogo em Cooperativismo", "formation_id": 1, "type_id": 3},
    {"name": "Tecnólogo em Agroindustrialização", "formation_id": 1, "type_id": 3},
    {"name": "Tecnólogo em Processamento de Alimentos", "formation_id": 1, "type_id": 3},
    {"name": "Tecnólogo em Tecnologia de Alimentos", "formation_id": 1, "type_id": 3},
    {"name": "Tecnólogo em Controle de Qualidade de Alimentos", "formation_id": 1, "type_id": 3},
    {"name": "Tecnólogo em Segurança Alimentar", "formation_id": 1, "type_id": 3},
    {"name": "Tecnólogo em Enologia", "formation_id": 1, "type_id": 3},
    {"name": "Tecnólogo em Cervejaria", "formation_id": 1, "type_id": 3},
    {"name": "Tecnólogo em Destilaria", "formation_id": 1, "type_id": 3},
    {"name": "Tecnólogo em Confeitaria", "formation_id": 1, "type_id": 3},
    {"name": "Tecnólogo em Padaria Artesanal", "formation_id": 1, "type_id": 3},
    {"name": "Tecnólogo em Laticínios", "formation_id": 1, "type_id": 3},
    {"name": "Tecnólogo em Carnes", "formation_id": 1, "type_id": 3},
    {"name": "Tecnólogo em Pescado", "formation_id": 1, "type_id": 3},
    {"name": "Tecnólogo em Oleaginosas", "formation_id": 1, "type_id": 3},
    {"name": "Tecnólogo em Óleos Essenciais", "formation_id": 1, "type_id": 3},
    {"name": "Tecnólogo em Cosmetologia", "formation_id": 1, "type_id": 3},
    {"name": "Tecnólogo em Química Cosmética", "formation_id": 1, "type_id": 3},
    {"name": "Tecnólogo em Farmacologia Aplicada", "formation_id": 1, "type_id": 3},
    {"name": "Tecnólogo em Controle Farmacêutico", "formation_id": 1, "type_id": 3},
    {"name": "Tecnólogo em Fitofarmácia", "formation_id": 1, "type_id": 3},
    {"name": "Tecnólogo em Homeopatia", "formation_id": 1, "type_id": 3},
    {"name": "Tecnólogo em Plantas Medicinais", "formation_id": 1, "type_id": 3},
    {"name": "Tecnólogo em Acupuntura", "formation_id": 1, "type_id": 3},
    {"name": "Tecnólogo em Naturologia", "formation_id": 1, "type_id": 3},
    {"name": "Tecnólogo em Terapias Holísticas", "formation_id": 1, "type_id": 3},
    {"name": "Tecnólogo em Reabilitação Física", "formation_id": 1, "type_id": 3},
    {"name": "Tecnólogo em Ergonomia", "formation_id": 1, "type_id": 3},
    {"name": "Tecnólogo em Biomecânica", "formation_id": 1, "type_id": 3},
    {"name": "Tecnólogo em Posturologia", "formation_id": 1, "type_id": 3},
    {"name": "Tecnólogo em Gerontologia", "formation_id": 1, "type_id": 3},
    {"name": "Tecnólogo em Cuidados com Idosos", "formation_id": 1, "type_id": 3},
    {"name": "Tecnólogo em Pediatria", "formation_id": 1, "type_id": 3},
    {"name": "Tecnólogo em Cardiologia", "formation_id": 1, "type_id": 3},
    {"name": "Tecnólogo em Oncologia", "formation_id": 1, "type_id": 3},
    {"name": "Tecnólogo em Oftalmologia", "formation_id": 1, "type_id": 3},
    {"name": "Tecnólogo em Otorrinolaringologia", "formation_id": 1, "type_id": 3},
    {"name": "Tecnólogo em Dermatologia", "formation_id": 1, "type_id": 3},
    {"name": "Tecnólogo em Ortopedia", "formation_id": 1, "type_id": 3},
    {"name": "Tecnólogo em Cirurgia", "formation_id": 1, "type_id": 3},
    {"name": "Tecnólogo em Anestesiologia", "formation_id": 1, "type_id": 3},
    {"name": "Tecnólogo em Hemoterapia", "formation_id": 1, "type_id": 3},
    {"name": "Tecnólogo em Imagenologia", "formation_id": 1, "type_id": 3},
    {"name": "Tecnólogo em Ultrassonografia", "formation_id": 1, "type_id": 3},
    {"name": "Tecnólogo em Ressonância Magnética", "formation_id": 1, "type_id": 3},
    {"name": "Tecnólogo em Anatomia Patológica", "formation_id": 1, "type_id": 3},
    {"name": "Tecnólogo em Citologia", "formation_id": 1, "type_id": 3},
    {"name": "Tecnólogo em Histologia", "formation_id": 1, "type_id": 3},
    {"name": "Tecnólogo em Hematologia", "formation_id": 1, "type_id": 3},
    {"name": "Tecnólogo em Imunologia", "formation_id": 1, "type_id": 3},
    {"name": "Tecnólogo em Microbiologia Clínica", "formation_id": 1, "type_id": 3},
    {"name": "Tecnólogo em Parasitologia", "formation_id": 1, "type_id": 3},
    {"name": "Tecnólogo em Micologia", "formation_id": 1, "type_id": 3},
    {"name": "Tecnólogo em Virologia", "formation_id": 1, "type_id": 3},
    {"name": "Tecnólogo em Epidemiologia", "formation_id": 1, "type_id": 3},
    {"name": "Tecnólogo em Vigilância Sanitária", "formation_id": 1, "type_id": 3},
    {"name": "Tecnólogo em Saúde Pública", "formation_id": 1, "type_id": 3},
    {"name": "Tecnólogo em Educação em Saúde", "formation_id": 1, "type_id": 3},
    {"name": "Tecnólogo em Promoção da Saúde", "formation_id": 1, "type_id": 3},
    {"name": "Tecnólogo em Prevenção de Doenças", "formation_id": 1, "type_id": 3},
    {"name": "Tecnólogo em Primeiros Socorros", "formation_id": 1, "type_id": 3},
    {"name": "Tecnólogo em Paramedicina", "formation_id": 1, "type_id": 3},
    {"name": "Tecnólogo em Emergência Médica", "formation_id": 1, "type_id": 3},
    {"name": "Tecnólogo em Segurança em Saúde", "formation_id": 1, "type_id": 3},
    {"name": "Tecnólogo em Gestão de Clínicas", "formation_id": 1, "type_id": 3},
    {"name": "Tecnólogo em Gestão de Laboratórios", "formation_id": 1, "type_id": 3},
    {"name": "Tecnólogo em Gestão de Farmácias", "formation_id": 1, "type_id": 3},
    {"name": "Tecnólogo em Gestão de Hospitais", "formation_id": 1, "type_id": 3},
    {"name": "Tecnólogo em Administração de Saúde", "formation_id": 1, "type_id": 3}
  ],
  "trainings": [
    {"name": "Python for Everybody", "provider": "Udemy", "type": "Curso", "category": "Programação"},
    {"name": "The Complete JavaScript Course", "provider": "Udemy", "type": "Curso", "category": "Programação"},
    {"name": "AWS Certified Solutions Architect", "provider": "Udemy", "type": "Curso", "category": "Cloud"},
    {"name": "Machine Learning A-Z", "provider": "Udemy", "type": "Curso", "category": "Data Science"},
    {"name": "Docker & Kubernetes", "provider": "Udemy", "type": "Curso", "category": "DevOps"},
    {"name": "React - The Complete Guide", "provider": "Udemy", "type": "Curso", "category": "Frontend"},
    {"name": "Angular - The Complete Guide", "provider": "Udemy", "type": "Curso", "category": "Frontend"},
    {"name": "Vue.js 3 - The Complete Guide", "provider": "Udemy", "type": "Curso", "category": "Frontend"},
    {"name": "Node.js - The Complete Guide", "provider": "Udemy", "type": "Curso", "category": "Backend"},
    {"name": "SQL and Database Design", "provider": "Udemy", "type": "Curso", "category": "Database"},
    {"name": "Java e Orientação a Objetos", "provider": "Alura", "type": "Curso", "category": "Programação"},
    {"name": "HTML5 e CSS3", "provider": "Alura", "type": "Curso", "category": "Frontend"},
    {"name": "GIT e Controle de Versão", "provider": "Alura", "type": "Curso", "category": "DevOps"},
    {"name": "Spring Boot", "provider": "Alura", "type": "Curso", "category": "Backend"},
    {"name": "Android com Kotlin", "provider": "Alura", "type": "Curso", "category": "Mobile"},
    {"name": "Banco de Dados com MongoDB", "provider": "Alura", "type": "Curso", "category": "Database"},
    {"name": "Agile com Scrum", "provider": "Alura", "type": "Curso", "category": "Gestão"},
    {"name": "UX/UI Design", "provider": "Alura", "type": "Curso", "category": "Design"},
    {"name": "Power BI", "provider": "Alura", "type": "Curso", "category": "Data Analytics"},
    {"name": "Segurança em API", "provider": "Alura", "type": "Curso", "category": "Segurança"},
    {"name": "Machine Learning by Andrew Ng", "provider": "Coursera", "type": "Curso", "category": "Data Science"},
    {"name": "Google Cloud Professional", "provider": "Coursera", "type": "Certificação", "category": "Cloud"},
    {"name": "Data Science Specialization", "provider": "Coursera", "type": "Especialização", "category": "Data Science"},
    {"name": "IBM Data Science Professional", "provider": "Coursera", "type": "Certificação", "category": "Data Science"},
    {"name": "Artificial Intelligence Basics", "provider": "Coursera", "type": "Curso", "category": "IA"},
    {"name": "Onboarding - Processos da Empresa", "provider": "Empresa", "type": "Treinamento", "category": "Processo"},
    {"name": "Segurança da Informação Corporativa", "provider": "Empresa", "type": "Treinamento", "category": "Segurança"},
    {"name": "Compliance e Ética Profissional", "provider": "Empresa", "type": "Treinamento", "category": "Compliance"},
    {"name": "Ferramentas de Colaboração - Teams", "provider": "Empresa", "type": "Treinamento", "category": "Ferramentas"},
    {"name": "ERP SAP - Uso Básico", "provider": "Empresa", "type": "Treinamento", "category": "ERP"},
    {"name": "CRM Salesforce - Básico", "provider": "Empresa", "type": "Treinamento", "category": "CRM"},
    {"name": "Liderança e Gestão de Pessoas", "provider": "Empresa", "type": "Treinamento", "category": "Gestão"},
    {"name": "Comunicação Efetiva", "provider": "Empresa", "type": "Treinamento", "category": "Soft Skills"},
    {"name": "Inteligência Emocional", "provider": "Empresa", "type": "Treinamento", "category": "Soft Skills"},
    {"name": "Excelência no Atendimento", "provider": "Empresa", "type": "Treinamento", "category": "Customer"},
    {"name": "Negociação e Fechamento", "provider": "Empresa", "type": "Treinamento", "category": "Vendas"},
    {"name": "Análise de Dados com Excel", "provider": "Empresa", "type": "Treinamento", "category": "Ferramentas"},
    {"name": "Programação em Python - Intermediário", "provider": "Empresa", "type": "Treinamento", "category": "Programação"},
    {"name": "Testes Automatizados com Selenium", "provider": "Empresa", "type": "Treinamento", "category": "QA"},
    {"name": "DevOps na Prática", "provider": "Empresa", "type": "Treinamento", "category": "DevOps"},
    {"name": "Metodologia Ágil - Scrum e Kanban", "provider": "Empresa", "type": "Treinamento", "category": "Gestão"},
    {"name": "Sustentabilidade Corporativa", "provider": "Empresa", "type": "Treinamento", "category": "ESG"},
    {"name": "Inovação e Criatividade", "provider": "Empresa", "type": "Treinamento", "category": "Desenvolvimento"},
    {"name": "Inteligência Artificial Prática", "provider": "Empresa", "type": "Treinamento", "category": "IA"},
    {"name": "Cybersecurity Essentials", "provider": "Empresa", "type": "Treinamento", "category": "Segurança"},
    {"name": "Leadership Foundations", "provider": "LinkedIn Learning", "type": "Curso", "category": "Gestão"},
    {"name": "Advanced Excel", "provider": "LinkedIn Learning", "type": "Curso", "category": "Ferramentas"},
    {"name": "Project Management Basics", "provider": "LinkedIn Learning", "type": "Curso", "category": "Gestão"},
    {"name": "Digital Marketing Fundamentals", "provider": "LinkedIn Learning", "type": "Curso", "category": "Marketing"},
    {"name": "Public Speaking", "provider": "LinkedIn Learning", "type": "Curso", "category": "Soft Skills"},
    {"name": "AWS - EC2 and Networking", "provider": "Pluralsight", "type": "Curso", "category": "Cloud"},
    {"name": "Kubernetes Fundamentals", "provider": "Pluralsight", "type": "Curso", "category": "DevOps"},
    {"name": "Cybersecurity Foundations", "provider": "Pluralsight", "type": "Curso", "category": "Segurança"},
    {"name": "C# Programming", "provider": "Pluralsight", "type": "Curso", "category": "Programação"},
    {"name": "JavaScript Advanced Concepts", "provider": "Pluralsight", "type": "Curso", "category": "Programação"},
    {"name": "Google Cloud Platform Basics", "provider": "Google Cloud", "type": "Curso", "category": "Cloud"},
    {"name": "BigQuery Fundamentals", "provider": "Google Cloud", "type": "Curso", "category": "Data Analytics"},
    {"name": "Google Cloud Security", "provider": "Google Cloud", "type": "Curso", "category": "Segurança"},
    {"name": "Terraform on Google Cloud", "provider": "Google Cloud", "type": "Curso", "category": "Infrastructure"},
    {"name": "AWS Cloud Practitioner", "provider": "AWS", "type": "Certificação", "category": "Cloud"},
    {"name": "AWS Solutions Architect Associate", "provider": "AWS", "type": "Certificação", "category": "Cloud"},
    {"name": "AWS Developer Associate", "provider": "AWS", "type": "Certificação", "category": "Cloud"},
    {"name": "AWS SysOps Administrator", "provider": "AWS", "type": "Certificação", "category": "Cloud"},
    {"name": "Azure Fundamentals", "provider": "Microsoft", "type": "Curso", "category": "Cloud"},
    {"name": "Azure Administrator", "provider": "Microsoft", "type": "Curso", "category": "Cloud"},
    {"name": "Azure Developer", "provider": "Microsoft", "type": "Curso", "category": "Cloud"},
    {"name": "Dynamics 365 CRM", "provider": "Microsoft", "type": "Curso", "category": "CRM"},
    {"name": "Python Advanced", "provider": "Udemy", "type": "Curso", "category": "Programação"},
    {"name": "C++ for Game Development", "provider": "Udemy", "type": "Curso", "category": "Programação"},
    {"name": "Go Programming Language", "provider": "Udemy", "type": "Curso", "category": "Programação"},
    {"name": "Rust Programming", "provider": "Udemy", "type": "Curso", "category": "Programação"},
    {"name": "Swift for iOS", "provider": "Udemy", "type": "Curso", "category": "Mobile"},
    {"name": "Kotlin for Android", "provider": "Udemy", "type": "Curso", "category": "Mobile"},
    {"name": "Flutter Development", "provider": "Udemy", "type": "Curso", "category": "Mobile"},
    {"name": "React Native", "provider": "Udemy", "type": "Curso", "category": "Mobile"},
    {"name": "Next.js Complete Guide", "provider": "Udemy", "type": "Curso", "category": "Frontend"},
    {"name": "Svelte Framework", "provider": "Udemy", "type": "Curso", "category": "Frontend"},
    {"name": "GraphQL Complete Course", "provider": "Udemy", "type": "Curso", "category": "Backend"},
    {"name": "REST API Design", "provider": "Udemy", "type": "Curso", "category": "Backend"},
    {"name": "Microservices Architecture", "provider": "Udemy", "type": "Curso", "category": "Backend"},
    {"name": "Serverless Computing", "provider": "Udemy", "type": "Curso", "category": "Cloud"},
    {"name": "Terraform & IaC", "provider": "Udemy", "type": "Curso", "category": "DevOps"},
    {"name": "Ansible Automation", "provider": "Udemy", "type": "Curso", "category": "DevOps"},
    {"name": "Jenkins CI/CD", "provider": "Udemy", "type": "Curso", "category": "DevOps"},
    {"name": "GitLab CI/CD", "provider": "Udemy", "type": "Curso", "category": "DevOps"},
    {"name": "Prometheus Monitoring", "provider": "Udemy", "type": "Curso", "category": "DevOps"},
    {"name": "PostgreSQL Advanced", "provider": "Udemy", "type": "Curso", "category": "Database"},
    {"name": "MySQL Optimization", "provider": "Udemy", "type": "Curso", "category": "Database"},
    {"name": "Redis Cache", "provider": "Udemy", "type": "Curso", "category": "Database"},
    {"name": "Elasticsearch Masterclass", "provider": "Udemy", "type": "Curso", "category": "Database"},
    {"name": "Apache Spark", "provider": "Udemy", "type": "Curso", "category": "Data Science"},
    {"name": "TensorFlow Deep Learning", "provider": "Udemy", "type": "Curso", "category": "Data Science"},
    {"name": "PyTorch Neural Networks", "provider": "Udemy", "type": "Curso", "category": "Data Science"},
    {"name": "NLP with Python", "provider": "Udemy", "type": "Curso", "category": "Data Science"},
    {"name": "Computer Vision", "provider": "Udemy", "type": "Curso", "category": "Data Science"},
    {"name": "Time Series Analysis", "provider": "Udemy", "type": "Curso", "category": "Data Science"},
    {"name": "Tableau Advanced", "provider": "Alura", "type": "Curso", "category": "Data Analytics"},
    {"name": "Looker Studio", "provider": "Alura", "type": "Curso", "category": "Data Analytics"},
    {"name": "Metabase", "provider": "Alura", "type": "Curso", "category": "Data Analytics"},
    {"name": "Superset", "provider": "Alura", "type": "Curso", "category": "Data Analytics"},
    {"name": "Google Analytics 4", "provider": "Alura", "type": "Curso", "category": "Data Analytics"},
    {"name": "Matomo Analytics", "provider": "Alura", "type": "Curso", "category": "Data Analytics"},
    {"name": "SEO Mastery", "provider": "Alura", "type": "Curso", "category": "Marketing"},
    {"name": "SEM Strategies", "provider": "Alura", "type": "Curso", "category": "Marketing"},
    {"name": "Social Media Marketing", "provider": "Alura", "type": "Curso", "category": "Marketing"},
    {"name": "Email Marketing", "provider": "Alura", "type": "Curso", "category": "Marketing"},
    {"name": "Content Marketing", "provider": "Alura", "type": "Curso", "category": "Marketing"},
    {"name": "Inbound Marketing", "provider": "Alura", "type": "Curso", "category": "Marketing"},
    {"name": "Growth Hacking", "provider": "Alura", "type": "Curso", "category": "Marketing"},
    {"name": "Marketing Automation", "provider": "Alura", "type": "Curso", "category": "Marketing"},
    {"name": "CRO - Conversion Rate Optimization", "provider": "Alura", "type": "Curso", "category": "Marketing"},
    {"name": "Copywriting", "provider": "Alura", "type": "Curso", "category": "Marketing"},
    {"name": "Branding Strategy", "provider": "Alura", "type": "Curso", "category": "Marketing"},
    {"name": "Market Research", "provider": "Alura", "type": "Curso", "category": "Marketing"},
    {"name": "Consumer Psychology", "provider": "Alura", "type": "Curso", "category": "Marketing"},
    {"name": "Behavioral Economics", "provider": "Coursera", "type": "Curso", "category": "Economia"},
    {"name": "Econometrics", "provider": "Coursera", "type": "Curso", "category": "Economia"},
    {"name": "International Trade", "provider": "Coursera", "type": "Curso", "category": "Economia"},
    {"name": "Development Economics", "provider": "Coursera", "type": "Curso", "category": "Economia"},
    {"name": "Financial Economics", "provider": "Coursera", "type": "Curso", "category": "Economia"},
    {"name": "Portfolio Management", "provider": "Coursera", "type": "Curso", "category": "Finanças"},
    {"name": "Options Trading", "provider": "Coursera", "type": "Curso", "category": "Finanças"},
    {"name": "Fixed Income Securities", "provider": "Coursera", "type": "Curso", "category": "Finanças"},
    {"name": "Corporate Finance", "provider": "Coursera", "type": "Curso", "category": "Finanças"},
    {"name": "Investment Banking", "provider": "Coursera", "type": "Curso", "category": "Finanças"},
    {"name": "Risk Management", "provider": "Coursera", "type": "Curso", "category": "Finanças"},
    {"name": "Insurance and Risk", "provider": "Coursera", "type": "Curso", "category": "Finanças"},
    {"name": "Blockchain Finance", "provider": "Coursera", "type": "Curso", "category": "Finanças"},
    {"name": "DeFi Protocols", "provider": "Coursera", "type": "Curso", "category": "Criptomoedas"},
    {"name": "Cryptocurrency Trading", "provider": "Coursera", "type": "Curso", "category": "Criptomoedas"},
    {"name": "Smart Contracts", "provider": "Coursera", "type": "Curso", "category": "Blockchain"},
    {"name": "Solidity Programming", "provider": "Coursera", "type": "Curso", "category": "Blockchain"},
    {"name": "Web3 Development", "provider": "Coursera", "type": "Curso", "category": "Blockchain"},
    {"name": "NFT Creation", "provider": "Coursera", "type": "Curso", "category": "Blockchain"},
    {"name": "UX Research", "provider": "Alura", "type": "Curso", "category": "Design"},
    {"name": "Interaction Design", "provider": "Alura", "type": "Curso", "category": "Design"},
    {"name": "Motion Design", "provider": "Alura", "type": "Curso", "category": "Design"},
    {"name": "Typography Mastery", "provider": "Alura", "type": "Curso", "category": "Design"},
    {"name": "Color Theory", "provider": "Alura", "type": "Curso", "category": "Design"},
    {"name": "Composition Design", "provider": "Alura", "type": "Curso", "category": "Design"},
    {"name": "Print Design", "provider": "Alura", "type": "Curso", "category": "Design"},
    {"name": "Package Design", "provider": "Alura", "type": "Curso", "category": "Design"},
    {"name": "Brand Identity", "provider": "Alura", "type": "Curso", "category": "Design"},
    {"name": "Logo Design", "provider": "Alura", "type": "Curso", "category": "Design"},
    {"name": "Icon Design", "provider": "Alura", "type": "Curso", "category": "Design"},
    {"name": "Web Design", "provider": "Alura", "type": "Curso", "category": "Design"},
    {"name": "Interface Design", "provider": "Alura", "type": "Curso", "category": "Design"},
    {"name": "3D Design", "provider": "Alura", "type": "Curso", "category": "Design"},
    {"name": "CAD Básico", "provider": "Alura", "type": "Curso", "category": "Design"},
    {"name": "Blender 3D", "provider": "Alura", "type": "Curso", "category": "Design"},
    {"name": "AutoCAD", "provider": "Alura", "type": "Curso", "category": "Design"},
    {"name": "SketchUp", "provider": "Alura", "type": "Curso", "category": "Design"},
    {"name": "Photoshop Avançado", "provider": "Alura", "type": "Curso", "category": "Design"},
    {"name": "Illustrator Mastery", "provider": "Alura", "type": "Curso", "category": "Design"},
    {"name": "InDesign Publishing", "provider": "Alura", "type": "Curso", "category": "Design"},
    {"name": "CorelDRAW", "provider": "Alura", "type": "Curso", "category": "Design"},
    {"name": "Figma UI/UX", "provider": "Alura", "type": "Curso", "category": "Design"},
    {"name": "Adobe XD", "provider": "Alura", "type": "Curso", "category": "Design"},
    {"name": "Sketch App", "provider": "Alura", "type": "Curso", "category": "Design"},
    {"name": "Prototyping with Figma", "provider": "Alura", "type": "Curso", "category": "Design"},
    {"name": "Wireframing", "provider": "Alura", "type": "Curso", "category": "Design"},
    {"name": "Design Systems", "provider": "Alura", "type": "Curso", "category": "Design"},
    {"name": "Accessibility in Design", "provider": "Alura", "type": "Curso", "category": "Design"},
    {"name": "Video Production", "provider": "Alura", "type": "Curso", "category": "Audiovisual"},
    {"name": "Cinematography", "provider": "Alura", "type": "Curso", "category": "Audiovisual"},
    {"name": "Lighting for Video", "provider": "Alura", "type": "Curso", "category": "Audiovisual"},
    {"name": "Color Grading", "provider": "Alura", "type": "Curso", "category": "Audiovisual"},
    {"name": "Video Editing with Premiere", "provider": "Alura", "type": "Curso", "category": "Audiovisual"},
    {"name": "DaVinci Resolve", "provider": "Alura", "type": "Curso", "category": "Audiovisual"},
    {"name": "After Effects VFX", "provider": "Alura", "type": "Curso", "category": "Audiovisual"},
    {"name": "Animation Principles", "provider": "Alura", "type": "Curso", "category": "Audiovisual"},
    {"name": "Motion Graphics", "provider": "Alura", "type": "Curso", "category": "Audiovisual"},
    {"name": "2D Animation", "provider": "Alura", "type": "Curso", "category": "Audiovisual"},
    {"name": "3D Animation", "provider": "Alura", "type": "Curso", "category": "Audiovisual"},
    {"name": "Stop Motion", "provider": "Alura", "type": "Curso", "category": "Audiovisual"},
    {"name": "Sound Design", "provider": "Alura", "type": "Curso", "category": "Audiovisual"},
    {"name": "Audio Mixing", "provider": "Alura", "type": "Curso", "category": "Audiovisual"},
    {"name": "Podcast Production", "provider": "Alura", "type": "Curso", "category": "Audiovisual"},
    {"name": "Music Composition", "provider": "Alura", "type": "Curso", "category": "Audiovisual"},
    {"name": "Digital Music Production", "provider": "Alura", "type": "Curso", "category": "Audiovisual"},
    {"name": "Ableton Live", "provider": "Alura", "type": "Curso", "category": "Audiovisual"},
    {"name": "FL Studio", "provider": "Alura", "type": "Curso", "category": "Audiovisual"},
    {"name": "Logic Pro", "provider": "Alura", "type": "Curso", "category": "Audiovisual"},
    {"name": "Pro Tools", "provider": "Alura", "type": "Curso", "category": "Audiovisual"},
    {"name": "MIDI Sequencing", "provider": "Alura", "type": "Curso", "category": "Audiovisual"},
    {"name": "Synthesis", "provider": "Alura", "type": "Curso", "category": "Audiovisual"},
    {"name": "Game Design", "provider": "Pluralsight", "type": "Curso", "category": "Game Dev"},
    {"name": "Game Architecture", "provider": "Pluralsight", "type": "Curso", "category": "Game Dev"},
    {"name": "Unity 3D Complete", "provider": "Pluralsight", "type": "Curso", "category": "Game Dev"},
    {"name": "Unreal Engine 5", "provider": "Pluralsight", "type": "Curso", "category": "Game Dev"},
    {"name": "Godot Engine", "provider": "Pluralsight", "type": "Curso", "category": "Game Dev"},
    {"name": "Game Physics", "provider": "Pluralsight", "type": "Curso", "category": "Game Dev"},
    {"name": "AI in Games", "provider": "Pluralsight", "type": "Curso", "category": "Game Dev"},
    {"name": "Multiplayer Game Development", "provider": "Pluralsight", "type": "Curso", "category": "Game Dev"},
    {"name": "Mobile Game Development", "provider": "Pluralsight", "type": "Curso", "category": "Game Dev"},
    {"name": "Narrative Design", "provider": "Pluralsight", "type": "Curso", "category": "Game Dev"}
  ]
}
